[
    {
        "stimulus":"stimuli\/whoopee_cushion\/whoopee_cushion_08s.jpg",
        "true_category":"Julty",
        "true_keyboard":"j"
    },
    {
        "stimulus":"stimuli\/clove\/clove_02s.jpg",
        "true_category":"Folty",
        "true_keyboard":"f"
    },
    {
        "stimulus":"stimuli\/frame\/frame_01b.jpg",
        "true_category":"Julty",
        "true_keyboard":"j"
    },
    {
        "stimulus":"stimuli\/awning\/awning_11s.jpg",
        "true_category":"Julty",
        "true_keyboard":"j"
    },
    {
        "stimulus":"stimuli\/rooster\/rooster_09s.jpg",
        "true_category":"Julty",
        "true_keyboard":"j"
    },
    {
        "stimulus":"stimuli\/bookshelf\/bookshelf_12s.jpg",
        "true_category":"Julty",
        "true_keyboard":"j"
    },
    {
        "stimulus":"stimuli\/tamale\/tamale_09s.jpg",
        "true_category":"Folty",
        "true_keyboard":"f"
    },
    {
        "stimulus":"stimuli\/counter\/counter_12s.jpg",
        "true_category":"Folty",
        "true_keyboard":"f"
    },
    {
        "stimulus":"stimuli\/taillight\/taillight_13s.jpg",
        "true_category":"Julty",
        "true_keyboard":"j"
    },
    {
        "stimulus":"stimuli\/star_fruit\/star_fruit_09s.jpg",
        "true_category":"Folty",
        "true_keyboard":"f"
    },
    {
        "stimulus":"stimuli\/whisk\/whisk_05s.jpg",
        "true_category":"Folty",
        "true_keyboard":"f"
    },
    {
        "stimulus":"stimuli\/tupperware\/tupperware_10s.jpg",
        "true_category":"Julty",
        "true_keyboard":"j"
    },
    {
        "stimulus":"stimuli\/fig\/fig_10s.jpg",
        "true_category":"Folty",
        "true_keyboard":"f"
    },
    {
        "stimulus":"stimuli\/beehive\/beehive_01b.jpg",
        "true_category":"Julty",
        "true_keyboard":"j"
    },
    {
        "stimulus":"stimuli\/measuring_cup\/measuring_cup_05s.jpg",
        "true_category":"Folty",
        "true_keyboard":"f"
    },
    {
        "stimulus":"stimuli\/rolling_pin\/rolling_pin_03s.jpg",
        "true_category":"Folty",
        "true_keyboard":"f"
    },
    {
        "stimulus":"stimuli\/pill\/pill_11s.jpg",
        "true_category":"Julty",
        "true_keyboard":"j"
    },
    {
        "stimulus":"stimuli\/lollipop\/lollipop_12s.jpg",
        "true_category":"Folty",
        "true_keyboard":"f"
    },
    {
        "stimulus":"stimuli\/chin\/chin_05s.jpg",
        "true_category":"Julty",
        "true_keyboard":"j"
    },
    {
        "stimulus":"stimuli\/candy_cane\/candy_cane_08s.jpg",
        "true_category":"Folty",
        "true_keyboard":"f"
    },
    {
        "stimulus":"stimuli\/silverware\/silverware_11s.jpg",
        "true_category":"Folty",
        "true_keyboard":"f"
    },
    {
        "stimulus":"stimuli\/eggbeater\/eggbeater_06s.jpg",
        "true_category":"Folty",
        "true_keyboard":"f"
    },
    {
        "stimulus":"stimuli\/wine\/wine_13s.jpg",
        "true_category":"Folty",
        "true_keyboard":"f"
    },
    {
        "stimulus":"stimuli\/maggot\/maggot_02s.jpg",
        "true_category":"Julty",
        "true_keyboard":"j"
    },
    {
        "stimulus":"stimuli\/pig\/pig_12s.jpg",
        "true_category":"Julty",
        "true_keyboard":"j"
    },
    {
        "stimulus":"stimuli\/sombrero\/sombrero_11s.jpg",
        "true_category":"Julty",
        "true_keyboard":"j"
    },
    {
        "stimulus":"stimuli\/oven\/oven_02s.jpg",
        "true_category":"Folty",
        "true_keyboard":"f"
    },
    {
        "stimulus":"stimuli\/nose\/nose_11s.jpg",
        "true_category":"Julty",
        "true_keyboard":"j"
    },
    {
        "stimulus":"stimuli\/coconut\/coconut_10s.jpg",
        "true_category":"Folty",
        "true_keyboard":"f"
    },
    {
        "stimulus":"stimuli\/fur_coat\/fur_coat_06s.jpg",
        "true_category":"Julty",
        "true_keyboard":"j"
    },
    {
        "stimulus":"stimuli\/latch\/latch_13s.jpg",
        "true_category":"Julty",
        "true_keyboard":"j"
    },
    {
        "stimulus":"stimuli\/toilet\/toilet_05s.jpg",
        "true_category":"Julty",
        "true_keyboard":"j"
    },
    {
        "stimulus":"stimuli\/pomegranate\/pomegranate_07s.jpg",
        "true_category":"Folty",
        "true_keyboard":"f"
    },
    {
        "stimulus":"stimuli\/envelope\/envelope_06s.jpg",
        "true_category":"Julty",
        "true_keyboard":"j"
    },
    {
        "stimulus":"stimuli\/tackle\/tackle_07s.jpg",
        "true_category":"Julty",
        "true_keyboard":"j"
    },
    {
        "stimulus":"stimuli\/sifter\/sifter_13s.jpg",
        "true_category":"Folty",
        "true_keyboard":"f"
    },
    {
        "stimulus":"stimuli\/frisbee\/frisbee_08s.jpg",
        "true_category":"Julty",
        "true_keyboard":"j"
    },
    {
        "stimulus":"stimuli\/juicer2\/juicer2_12s.jpg",
        "true_category":"Folty",
        "true_keyboard":"f"
    },
    {
        "stimulus":"stimuli\/strawberry\/strawberry_14n.jpg",
        "true_category":"Folty",
        "true_keyboard":"f"
    },
    {
        "stimulus":"stimuli\/toothbrush\/toothbrush_05s.jpg",
        "true_category":"Julty",
        "true_keyboard":"j"
    },
    {
        "stimulus":"stimuli\/pan\/pan_16s.jpg",
        "true_category":"Folty",
        "true_keyboard":"f"
    },
    {
        "stimulus":"stimuli\/clam\/clam_10s.jpg",
        "true_category":"Folty",
        "true_keyboard":"f"
    },
    {
        "stimulus":"stimuli\/dishwashing_liquid\/dishwashing_liquid_04s.jpg",
        "true_category":"Julty",
        "true_keyboard":"j"
    },
    {
        "stimulus":"stimuli\/smoothie\/smoothie_13s.jpg",
        "true_category":"Folty",
        "true_keyboard":"f"
    },
    {
        "stimulus":"stimuli\/caviar\/caviar_01b.jpg",
        "true_category":"Folty",
        "true_keyboard":"f"
    },
    {
        "stimulus":"stimuli\/gum\/gum_02s.jpg",
        "true_category":"Folty",
        "true_keyboard":"f"
    },
    {
        "stimulus":"stimuli\/teabag\/teabag_06s.jpg",
        "true_category":"Folty",
        "true_keyboard":"f"
    },
    {
        "stimulus":"stimuli\/timer\/timer_08s.jpg",
        "true_category":"Julty",
        "true_keyboard":"j"
    },
    {
        "stimulus":"stimuli\/dishrag\/dishrag_06s.jpg",
        "true_category":"Julty",
        "true_keyboard":"j"
    },
    {
        "stimulus":"stimuli\/jump_rope\/jump_rope_02s.jpg",
        "true_category":"Julty",
        "true_keyboard":"j"
    },
    {
        "stimulus":"stimuli\/iceskate\/iceskate_13s.jpg",
        "true_category":"Julty",
        "true_keyboard":"j"
    },
    {
        "stimulus":"stimuli\/waffle_iron\/waffle_iron_04s.jpg",
        "true_category":"Folty",
        "true_keyboard":"f"
    },
    {
        "stimulus":"stimuli\/fox\/fox_16s.jpg",
        "true_category":"Julty",
        "true_keyboard":"j"
    },
    {
        "stimulus":"stimuli\/cannonball\/cannonball_01b.jpg",
        "true_category":"Julty",
        "true_keyboard":"j"
    },
    {
        "stimulus":"stimuli\/kettle\/kettle_10s.jpg",
        "true_category":"Folty",
        "true_keyboard":"f"
    },
    {
        "stimulus":"stimuli\/bok_choy\/bok_choy_15s.jpg",
        "true_category":"Folty",
        "true_keyboard":"f"
    },
    {
        "stimulus":"stimuli\/mint\/mint_06s.jpg",
        "true_category":"Folty",
        "true_keyboard":"f"
    },
    {
        "stimulus":"stimuli\/gold\/gold_15s.jpg",
        "true_category":"Julty",
        "true_keyboard":"j"
    },
    {
        "stimulus":"stimuli\/shopping_basket\/shopping_basket_01b.jpg",
        "true_category":"Julty",
        "true_keyboard":"j"
    },
    {
        "stimulus":"stimuli\/keg\/keg_18s.jpg",
        "true_category":"Julty",
        "true_keyboard":"j"
    },
    {
        "stimulus":"stimuli\/glass\/glass_07s.jpg",
        "true_category":"Julty",
        "true_keyboard":"j"
    },
    {
        "stimulus":"stimuli\/tea\/tea_03s.jpg",
        "true_category":"Folty",
        "true_keyboard":"f"
    },
    {
        "stimulus":"stimuli\/monkey\/monkey_18n.jpg",
        "true_category":"Julty",
        "true_keyboard":"j"
    },
    {
        "stimulus":"stimuli\/water_fountain\/water_fountain_01b.jpg",
        "true_category":"Julty",
        "true_keyboard":"j"
    },
    {
        "stimulus":"stimuli\/shell2\/shell2_01b.jpg",
        "true_category":"Julty",
        "true_keyboard":"j"
    },
    {
        "stimulus":"stimuli\/blueberry\/blueberry_10s.jpg",
        "true_category":"Folty",
        "true_keyboard":"f"
    },
    {
        "stimulus":"stimuli\/glasses\/glasses_09s.jpg",
        "true_category":"Julty",
        "true_keyboard":"j"
    },
    {
        "stimulus":"stimuli\/pepper1\/pepper1_05s.jpg",
        "true_category":"Folty",
        "true_keyboard":"f"
    },
    {
        "stimulus":"stimuli\/kiwi\/kiwi_06s.jpg",
        "true_category":"Folty",
        "true_keyboard":"f"
    },
    {
        "stimulus":"stimuli\/apple_tree\/apple_tree_08s.jpg",
        "true_category":"Folty",
        "true_keyboard":"f"
    },
    {
        "stimulus":"stimuli\/chocolate\/chocolate_06s.jpg",
        "true_category":"Folty",
        "true_keyboard":"f"
    },
    {
        "stimulus":"stimuli\/salami\/salami_11s.jpg",
        "true_category":"Folty",
        "true_keyboard":"f"
    },
    {
        "stimulus":"stimuli\/orange_rind\/orange_rind_16s.jpg",
        "true_category":"Folty",
        "true_keyboard":"f"
    },
    {
        "stimulus":"stimuli\/okra\/okra_08s.jpg",
        "true_category":"Folty",
        "true_keyboard":"f"
    },
    {
        "stimulus":"stimuli\/baseball_glove\/baseball_glove_06s.jpg",
        "true_category":"Julty",
        "true_keyboard":"j"
    },
    {
        "stimulus":"stimuli\/bouquet\/bouquet_04s.jpg",
        "true_category":"Julty",
        "true_keyboard":"j"
    },
    {
        "stimulus":"stimuli\/soap\/soap_02s.jpg",
        "true_category":"Julty",
        "true_keyboard":"j"
    },
    {
        "stimulus":"stimuli\/mud\/mud_04s.jpg",
        "true_category":"Julty",
        "true_keyboard":"j"
    },
    {
        "stimulus":"stimuli\/shaker\/shaker_01b.jpg",
        "true_category":"Julty",
        "true_keyboard":"j"
    },
    {
        "stimulus":"stimuli\/ice_cube\/ice_cube_08s.jpg",
        "true_category":"Folty",
        "true_keyboard":"f"
    },
    {
        "stimulus":"stimuli\/barrel\/barrel_05s.jpg",
        "true_category":"Julty",
        "true_keyboard":"j"
    },
    {
        "stimulus":"stimuli\/espresso\/espresso_08s.jpg",
        "true_category":"Folty",
        "true_keyboard":"f"
    },
    {
        "stimulus":"stimuli\/birthday_cake\/birthday_cake_03s.jpg",
        "true_category":"Folty",
        "true_keyboard":"f"
    },
    {
        "stimulus":"stimuli\/sundae\/sundae_07s.jpg",
        "true_category":"Folty",
        "true_keyboard":"f"
    },
    {
        "stimulus":"stimuli\/sugar_cube\/sugar_cube_02s.jpg",
        "true_category":"Folty",
        "true_keyboard":"f"
    },
    {
        "stimulus":"stimuli\/snail\/snail_01b.jpg",
        "true_category":"Julty",
        "true_keyboard":"j"
    },
    {
        "stimulus":"stimuli\/flour\/flour_09s.jpg",
        "true_category":"Folty",
        "true_keyboard":"f"
    },
    {
        "stimulus":"stimuli\/spoon\/spoon_01b.jpg",
        "true_category":"Folty",
        "true_keyboard":"f"
    },
    {
        "stimulus":"stimuli\/tongue\/tongue_08s.jpg",
        "true_category":"Julty",
        "true_keyboard":"j"
    },
    {
        "stimulus":"stimuli\/cotton_candy\/cotton_candy_11s.jpg",
        "true_category":"Folty",
        "true_keyboard":"f"
    },
    {
        "stimulus":"stimuli\/sorbet\/sorbet_11s.jpg",
        "true_category":"Folty",
        "true_keyboard":"f"
    },
    {
        "stimulus":"stimuli\/cage\/cage_10s.jpg",
        "true_category":"Julty",
        "true_keyboard":"j"
    },
    {
        "stimulus":"stimuli\/latte\/latte_04s.jpg",
        "true_category":"Folty",
        "true_keyboard":"f"
    },
    {
        "stimulus":"stimuli\/licorice\/licorice_07s.jpg",
        "true_category":"Folty",
        "true_keyboard":"f"
    },
    {
        "stimulus":"stimuli\/almond\/almond_10s.jpg",
        "true_category":"Folty",
        "true_keyboard":"f"
    },
    {
        "stimulus":"stimuli\/crumb\/crumb_08s.jpg",
        "true_category":"Folty",
        "true_keyboard":"f"
    },
    {
        "stimulus":"stimuli\/garlic\/garlic_01b.jpg",
        "true_category":"Folty",
        "true_keyboard":"f"
    },
    {
        "stimulus":"stimuli\/syrup\/syrup_08s.jpg",
        "true_category":"Folty",
        "true_keyboard":"f"
    },
    {
        "stimulus":"stimuli\/collar\/collar_13s.jpg",
        "true_category":"Julty",
        "true_keyboard":"j"
    },
    {
        "stimulus":"stimuli\/sweeper\/sweeper_11s.jpg",
        "true_category":"Julty",
        "true_keyboard":"j"
    },
    {
        "stimulus":"stimuli\/mussel\/mussel_07s.jpg",
        "true_category":"Folty",
        "true_keyboard":"f"
    },
    {
        "stimulus":"stimuli\/rake\/rake_14s.jpg",
        "true_category":"Julty",
        "true_keyboard":"j"
    },
    {
        "stimulus":"stimuli\/radish\/radish_11s.jpg",
        "true_category":"Folty",
        "true_keyboard":"f"
    },
    {
        "stimulus":"stimuli\/cooler\/cooler_04s.jpg",
        "true_category":"Julty",
        "true_keyboard":"j"
    },
    {
        "stimulus":"stimuli\/berry\/berry_02s.jpg",
        "true_category":"Folty",
        "true_keyboard":"f"
    },
    {
        "stimulus":"stimuli\/sleeping_bag\/sleeping_bag_07s.jpg",
        "true_category":"Julty",
        "true_keyboard":"j"
    },
    {
        "stimulus":"stimuli\/fungus\/fungus_08s.jpg",
        "true_category":"Julty",
        "true_keyboard":"j"
    },
    {
        "stimulus":"stimuli\/bison\/bison_10s.jpg",
        "true_category":"Julty",
        "true_keyboard":"j"
    },
    {
        "stimulus":"stimuli\/branch\/branch_04s.jpg",
        "true_category":"Julty",
        "true_keyboard":"j"
    },
    {
        "stimulus":"stimuli\/dish\/dish_02s.jpg",
        "true_category":"Folty",
        "true_keyboard":"f"
    },
    {
        "stimulus":"stimuli\/spur\/spur_06s.jpg",
        "true_category":"Julty",
        "true_keyboard":"j"
    },
    {
        "stimulus":"stimuli\/toothpick\/toothpick_15n.jpg",
        "true_category":"Julty",
        "true_keyboard":"j"
    },
    {
        "stimulus":"stimuli\/melon\/melon_12s.jpg",
        "true_category":"Folty",
        "true_keyboard":"f"
    },
    {
        "stimulus":"stimuli\/apple\/apple_06s.jpg",
        "true_category":"Folty",
        "true_keyboard":"f"
    },
    {
        "stimulus":"stimuli\/taffy\/taffy_05s.jpg",
        "true_category":"Folty",
        "true_keyboard":"f"
    },
    {
        "stimulus":"stimuli\/cart\/cart_10s.jpg",
        "true_category":"Julty",
        "true_keyboard":"j"
    },
    {
        "stimulus":"stimuli\/pearl\/pearl_08s.jpg",
        "true_category":"Julty",
        "true_keyboard":"j"
    },
    {
        "stimulus":"stimuli\/football_helmet\/football_helmet_14s.jpg",
        "true_category":"Julty",
        "true_keyboard":"j"
    },
    {
        "stimulus":"stimuli\/denture\/denture_04s.jpg",
        "true_category":"Julty",
        "true_keyboard":"j"
    },
    {
        "stimulus":"stimuli\/corsage\/corsage_06s.jpg",
        "true_category":"Julty",
        "true_keyboard":"j"
    }
]