[
    {
        "stimulus":"stimuli\/shark\/shark_12s.jpg",
        "true_category":"Folty",
        "true_keyboard":"f"
    },
    {
        "stimulus":"stimuli\/christmas_card\/christmas_card_05s.jpg",
        "true_category":"Julty",
        "true_keyboard":"j"
    },
    {
        "stimulus":"stimuli\/clove\/clove_03s.jpg",
        "true_category":"Julty",
        "true_keyboard":"j"
    },
    {
        "stimulus":"stimuli\/marijuana\/marijuana_01b.jpg",
        "true_category":"Julty",
        "true_keyboard":"j"
    },
    {
        "stimulus":"stimuli\/blinder\/blinder_04s.jpg",
        "true_category":"Folty",
        "true_keyboard":"f"
    },
    {
        "stimulus":"stimuli\/ladybug\/ladybug_02s.jpg",
        "true_category":"Folty",
        "true_keyboard":"f"
    },
    {
        "stimulus":"stimuli\/lavender\/lavender_04s.jpg",
        "true_category":"Julty",
        "true_keyboard":"j"
    },
    {
        "stimulus":"stimuli\/turban\/turban_06s.jpg",
        "true_category":"Julty",
        "true_keyboard":"j"
    },
    {
        "stimulus":"stimuli\/lobster\/lobster_04s.jpg",
        "true_category":"Folty",
        "true_keyboard":"f"
    },
    {
        "stimulus":"stimuli\/seafood\/seafood_04s.jpg",
        "true_category":"Julty",
        "true_keyboard":"j"
    },
    {
        "stimulus":"stimuli\/flower\/flower_16s.jpg",
        "true_category":"Julty",
        "true_keyboard":"j"
    },
    {
        "stimulus":"stimuli\/octopus\/octopus_10s.jpg",
        "true_category":"Folty",
        "true_keyboard":"f"
    },
    {
        "stimulus":"stimuli\/ear\/ear_11s.jpg",
        "true_category":"Julty",
        "true_keyboard":"j"
    },
    {
        "stimulus":"stimuli\/catfish\/catfish_08s.jpg",
        "true_category":"Folty",
        "true_keyboard":"f"
    },
    {
        "stimulus":"stimuli\/cauliflower\/cauliflower_06s.jpg",
        "true_category":"Julty",
        "true_keyboard":"j"
    },
    {
        "stimulus":"stimuli\/seagull\/seagull_11s.jpg",
        "true_category":"Folty",
        "true_keyboard":"f"
    },
    {
        "stimulus":"stimuli\/piggy_bank\/piggy_bank_01b.jpg",
        "true_category":"Folty",
        "true_keyboard":"f"
    },
    {
        "stimulus":"stimuli\/mosquito\/mosquito_05s.jpg",
        "true_category":"Folty",
        "true_keyboard":"f"
    },
    {
        "stimulus":"stimuli\/cantaloupe\/cantaloupe_09s.jpg",
        "true_category":"Julty",
        "true_keyboard":"j"
    },
    {
        "stimulus":"stimuli\/sewage\/sewage_13s.jpg",
        "true_category":"Julty",
        "true_keyboard":"j"
    },
    {
        "stimulus":"stimuli\/dolphin\/dolphin_05s.jpg",
        "true_category":"Folty",
        "true_keyboard":"f"
    },
    {
        "stimulus":"stimuli\/plaster_cast\/plaster_cast_10s.jpg",
        "true_category":"Julty",
        "true_keyboard":"j"
    },
    {
        "stimulus":"stimuli\/apple\/apple_02s.jpg",
        "true_category":"Julty",
        "true_keyboard":"j"
    },
    {
        "stimulus":"stimuli\/worm\/worm_02s.jpg",
        "true_category":"Folty",
        "true_keyboard":"f"
    },
    {
        "stimulus":"stimuli\/beet\/beet_06s.jpg",
        "true_category":"Julty",
        "true_keyboard":"j"
    },
    {
        "stimulus":"stimuli\/raisin\/raisin_09s.jpg",
        "true_category":"Julty",
        "true_keyboard":"j"
    },
    {
        "stimulus":"stimuli\/boat\/boat_07n.jpg",
        "true_category":"Julty",
        "true_keyboard":"j"
    },
    {
        "stimulus":"stimuli\/teddy_bear\/teddy_bear_01b.jpg",
        "true_category":"Folty",
        "true_keyboard":"f"
    },
    {
        "stimulus":"stimuli\/butterfly\/butterfly_07s.jpg",
        "true_category":"Folty",
        "true_keyboard":"f"
    },
    {
        "stimulus":"stimuli\/stump\/stump_04s.jpg",
        "true_category":"Julty",
        "true_keyboard":"j"
    },
    {
        "stimulus":"stimuli\/squid\/squid_11s.jpg",
        "true_category":"Folty",
        "true_keyboard":"f"
    },
    {
        "stimulus":"stimuli\/praying_mantis\/praying_mantis_15s.jpg",
        "true_category":"Folty",
        "true_keyboard":"f"
    },
    {
        "stimulus":"stimuli\/canoe\/canoe_03s.jpg",
        "true_category":"Julty",
        "true_keyboard":"j"
    },
    {
        "stimulus":"stimuli\/braid\/braid_12s.jpg",
        "true_category":"Julty",
        "true_keyboard":"j"
    },
    {
        "stimulus":"stimuli\/coverall\/coverall_01b.jpg",
        "true_category":"Julty",
        "true_keyboard":"j"
    },
    {
        "stimulus":"stimuli\/kiwi\/kiwi_09s.jpg",
        "true_category":"Julty",
        "true_keyboard":"j"
    },
    {
        "stimulus":"stimuli\/scorpion\/scorpion_09s.jpg",
        "true_category":"Folty",
        "true_keyboard":"f"
    },
    {
        "stimulus":"stimuli\/stingray\/stingray_09s.jpg",
        "true_category":"Folty",
        "true_keyboard":"f"
    },
    {
        "stimulus":"stimuli\/fishbowl\/fishbowl_15s.jpg",
        "true_category":"Folty",
        "true_keyboard":"f"
    },
    {
        "stimulus":"stimuli\/painting\/painting_04s.jpg",
        "true_category":"Julty",
        "true_keyboard":"j"
    },
    {
        "stimulus":"stimuli\/sonogram\/sonogram_08s.jpg",
        "true_category":"Folty",
        "true_keyboard":"f"
    },
    {
        "stimulus":"stimuli\/bathtub\/bathtub_23s.jpg",
        "true_category":"Julty",
        "true_keyboard":"j"
    },
    {
        "stimulus":"stimuli\/hoe\/hoe_10s.jpg",
        "true_category":"Julty",
        "true_keyboard":"j"
    },
    {
        "stimulus":"stimuli\/chime\/chime_01b.jpg",
        "true_category":"Julty",
        "true_keyboard":"j"
    },
    {
        "stimulus":"stimuli\/cocoon\/cocoon_10s.jpg",
        "true_category":"Folty",
        "true_keyboard":"f"
    },
    {
        "stimulus":"stimuli\/fur_coat\/fur_coat_01b.jpg",
        "true_category":"Julty",
        "true_keyboard":"j"
    },
    {
        "stimulus":"stimuli\/mantle\/mantle_10s.jpg",
        "true_category":"Julty",
        "true_keyboard":"j"
    },
    {
        "stimulus":"stimuli\/juicer2\/juicer2_13s.jpg",
        "true_category":"Julty",
        "true_keyboard":"j"
    },
    {
        "stimulus":"stimuli\/blowfish\/blowfish_04s.jpg",
        "true_category":"Folty",
        "true_keyboard":"f"
    },
    {
        "stimulus":"stimuli\/goldfish\/goldfish_04s.jpg",
        "true_category":"Folty",
        "true_keyboard":"f"
    },
    {
        "stimulus":"stimuli\/earwig\/earwig_09s.jpg",
        "true_category":"Folty",
        "true_keyboard":"f"
    },
    {
        "stimulus":"stimuli\/gutter\/gutter_09s.jpg",
        "true_category":"Julty",
        "true_keyboard":"j"
    },
    {
        "stimulus":"stimuli\/pogo_stick\/pogo_stick_03s.jpg",
        "true_category":"Julty",
        "true_keyboard":"j"
    },
    {
        "stimulus":"stimuli\/chariot\/chariot_03s.jpg",
        "true_category":"Julty",
        "true_keyboard":"j"
    },
    {
        "stimulus":"stimuli\/coal\/coal_09s.jpg",
        "true_category":"Julty",
        "true_keyboard":"j"
    },
    {
        "stimulus":"stimuli\/bacon\/bacon_02s.jpg",
        "true_category":"Julty",
        "true_keyboard":"j"
    },
    {
        "stimulus":"stimuli\/tarantula\/tarantula_03s.jpg",
        "true_category":"Folty",
        "true_keyboard":"f"
    },
    {
        "stimulus":"stimuli\/tadpole\/tadpole_12s.jpg",
        "true_category":"Folty",
        "true_keyboard":"f"
    },
    {
        "stimulus":"stimuli\/ant\/ant_09s.jpg",
        "true_category":"Folty",
        "true_keyboard":"f"
    },
    {
        "stimulus":"stimuli\/trap\/trap_06s.jpg",
        "true_category":"Folty",
        "true_keyboard":"f"
    },
    {
        "stimulus":"stimuli\/fly\/fly_05s.jpg",
        "true_category":"Folty",
        "true_keyboard":"f"
    },
    {
        "stimulus":"stimuli\/grasshopper\/grasshopper_05s.jpg",
        "true_category":"Folty",
        "true_keyboard":"f"
    },
    {
        "stimulus":"stimuli\/caterpillar\/caterpillar_05s.jpg",
        "true_category":"Folty",
        "true_keyboard":"f"
    },
    {
        "stimulus":"stimuli\/boa\/boa_11s.jpg",
        "true_category":"Julty",
        "true_keyboard":"j"
    },
    {
        "stimulus":"stimuli\/shrimp\/shrimp_07n.jpg",
        "true_category":"Folty",
        "true_keyboard":"f"
    },
    {
        "stimulus":"stimuli\/grapevine\/grapevine_04s.jpg",
        "true_category":"Folty",
        "true_keyboard":"f"
    },
    {
        "stimulus":"stimuli\/whale\/whale_05s.jpg",
        "true_category":"Folty",
        "true_keyboard":"f"
    },
    {
        "stimulus":"stimuli\/paper_towel\/paper_towel_14s.jpg",
        "true_category":"Julty",
        "true_keyboard":"j"
    },
    {
        "stimulus":"stimuli\/weather_vane\/weather_vane_19s.jpg",
        "true_category":"Folty",
        "true_keyboard":"f"
    },
    {
        "stimulus":"stimuli\/spider\/spider_10n.jpg",
        "true_category":"Folty",
        "true_keyboard":"f"
    },
    {
        "stimulus":"stimuli\/dumbwaiter\/dumbwaiter_04s.jpg",
        "true_category":"Julty",
        "true_keyboard":"j"
    },
    {
        "stimulus":"stimuli\/chest1\/chest1_07s.jpg",
        "true_category":"Julty",
        "true_keyboard":"j"
    },
    {
        "stimulus":"stimuli\/tick\/tick_06s.jpg",
        "true_category":"Folty",
        "true_keyboard":"f"
    },
    {
        "stimulus":"stimuli\/chisel\/chisel_13s.jpg",
        "true_category":"Julty",
        "true_keyboard":"j"
    },
    {
        "stimulus":"stimuli\/poster\/poster_02s.jpg",
        "true_category":"Julty",
        "true_keyboard":"j"
    },
    {
        "stimulus":"stimuli\/rocking_horse\/rocking_horse_01s.jpg",
        "true_category":"Folty",
        "true_keyboard":"f"
    },
    {
        "stimulus":"stimuli\/wall\/wall_10s.jpg",
        "true_category":"Julty",
        "true_keyboard":"j"
    },
    {
        "stimulus":"stimuli\/flypaper\/flypaper_07s.jpg",
        "true_category":"Julty",
        "true_keyboard":"j"
    },
    {
        "stimulus":"stimuli\/fossil\/fossil_09s.jpg",
        "true_category":"Folty",
        "true_keyboard":"f"
    },
    {
        "stimulus":"stimuli\/cockroach\/cockroach_07s.jpg",
        "true_category":"Folty",
        "true_keyboard":"f"
    },
    {
        "stimulus":"stimuli\/bee\/bee_27s.jpg",
        "true_category":"Folty",
        "true_keyboard":"f"
    },
    {
        "stimulus":"stimuli\/coaster\/coaster_10s.jpg",
        "true_category":"Julty",
        "true_keyboard":"j"
    },
    {
        "stimulus":"stimuli\/fire_alarm\/fire_alarm_15s.jpg",
        "true_category":"Julty",
        "true_keyboard":"j"
    },
    {
        "stimulus":"stimuli\/maggot\/maggot_01b.jpg",
        "true_category":"Folty",
        "true_keyboard":"f"
    },
    {
        "stimulus":"stimuli\/inhaler\/inhaler_01b.jpg",
        "true_category":"Julty",
        "true_keyboard":"j"
    },
    {
        "stimulus":"stimuli\/slug\/slug_02s.jpg",
        "true_category":"Folty",
        "true_keyboard":"f"
    },
    {
        "stimulus":"stimuli\/toe\/toe_13s.jpg",
        "true_category":"Julty",
        "true_keyboard":"j"
    },
    {
        "stimulus":"stimuli\/bird\/bird_06s.jpg",
        "true_category":"Folty",
        "true_keyboard":"f"
    },
    {
        "stimulus":"stimuli\/lamb_chop\/lamb_chop_07s.jpg",
        "true_category":"Julty",
        "true_keyboard":"j"
    },
    {
        "stimulus":"stimuli\/jet\/jet_08s.jpg",
        "true_category":"Julty",
        "true_keyboard":"j"
    },
    {
        "stimulus":"stimuli\/minivan\/minivan_11s.jpg",
        "true_category":"Julty",
        "true_keyboard":"j"
    },
    {
        "stimulus":"stimuli\/snake\/snake_05s.jpg",
        "true_category":"Folty",
        "true_keyboard":"f"
    },
    {
        "stimulus":"stimuli\/eye\/eye_02s.jpg",
        "true_category":"Folty",
        "true_keyboard":"f"
    },
    {
        "stimulus":"stimuli\/seahorse\/seahorse_08s.jpg",
        "true_category":"Folty",
        "true_keyboard":"f"
    },
    {
        "stimulus":"stimuli\/buggy\/buggy_08s.jpg",
        "true_category":"Julty",
        "true_keyboard":"j"
    },
    {
        "stimulus":"stimuli\/snail\/snail_17n.jpg",
        "true_category":"Folty",
        "true_keyboard":"f"
    },
    {
        "stimulus":"stimuli\/racehorse\/racehorse_04s.jpg",
        "true_category":"Folty",
        "true_keyboard":"f"
    },
    {
        "stimulus":"stimuli\/paperclip\/paperclip_02s.jpg",
        "true_category":"Julty",
        "true_keyboard":"j"
    },
    {
        "stimulus":"stimuli\/snowman\/snowman_03s.jpg",
        "true_category":"Julty",
        "true_keyboard":"j"
    },
    {
        "stimulus":"stimuli\/bug\/bug_17s.jpg",
        "true_category":"Folty",
        "true_keyboard":"f"
    },
    {
        "stimulus":"stimuli\/mushroom\/mushroom_11n.jpg",
        "true_category":"Folty",
        "true_keyboard":"f"
    },
    {
        "stimulus":"stimuli\/lightning_bug\/lightning_bug_07s.jpg",
        "true_category":"Folty",
        "true_keyboard":"f"
    },
    {
        "stimulus":"stimuli\/eel\/eel_03s.jpg",
        "true_category":"Folty",
        "true_keyboard":"f"
    },
    {
        "stimulus":"stimuli\/swordfish\/swordfish_01b.jpg",
        "true_category":"Folty",
        "true_keyboard":"f"
    },
    {
        "stimulus":"stimuli\/fish\/fish_12s.jpg",
        "true_category":"Folty",
        "true_keyboard":"f"
    },
    {
        "stimulus":"stimuli\/gargoyle\/gargoyle_09s.jpg",
        "true_category":"Folty",
        "true_keyboard":"f"
    },
    {
        "stimulus":"stimuli\/stair\/stair_12s.jpg",
        "true_category":"Julty",
        "true_keyboard":"j"
    },
    {
        "stimulus":"stimuli\/branch\/branch_04s.jpg",
        "true_category":"Julty",
        "true_keyboard":"j"
    },
    {
        "stimulus":"stimuli\/sunglasses\/sunglasses_06s.jpg",
        "true_category":"Julty",
        "true_keyboard":"j"
    },
    {
        "stimulus":"stimuli\/clam\/clam_10s.jpg",
        "true_category":"Julty",
        "true_keyboard":"j"
    },
    {
        "stimulus":"stimuli\/beehive\/beehive_10s.jpg",
        "true_category":"Julty",
        "true_keyboard":"j"
    },
    {
        "stimulus":"stimuli\/platypus\/platypus_02s.jpg",
        "true_category":"Folty",
        "true_keyboard":"f"
    },
    {
        "stimulus":"stimuli\/penguin\/penguin_01b.jpg",
        "true_category":"Folty",
        "true_keyboard":"f"
    },
    {
        "stimulus":"stimuli\/beetle\/beetle_10s.jpg",
        "true_category":"Folty",
        "true_keyboard":"f"
    },
    {
        "stimulus":"stimuli\/olive\/olive_04s.jpg",
        "true_category":"Julty",
        "true_keyboard":"j"
    },
    {
        "stimulus":"stimuli\/parrot\/parrot_04s.jpg",
        "true_category":"Folty",
        "true_keyboard":"f"
    },
    {
        "stimulus":"stimuli\/wheat\/wheat_06s.jpg",
        "true_category":"Julty",
        "true_keyboard":"j"
    },
    {
        "stimulus":"stimuli\/barrette\/barrette_01b.jpg",
        "true_category":"Julty",
        "true_keyboard":"j"
    },
    {
        "stimulus":"stimuli\/flute\/flute_05s.jpg",
        "true_category":"Julty",
        "true_keyboard":"j"
    },
    {
        "stimulus":"stimuli\/wasp\/wasp_03s.jpg",
        "true_category":"Folty",
        "true_keyboard":"f"
    }
]