[
    {
        "stimulus":"stimuli\/payphone\/payphone_10s.jpg",
        "true_category":"Folty",
        "true_keyboard":"f"
    },
    {
        "stimulus":"stimuli\/tuning_fork\/tuning_fork_11s.jpg",
        "true_category":"Folty",
        "true_keyboard":"f"
    },
    {
        "stimulus":"stimuli\/trigger\/trigger_02s.jpg",
        "true_category":"Folty",
        "true_keyboard":"f"
    },
    {
        "stimulus":"stimuli\/tile\/tile_09s.jpg",
        "true_category":"Julty",
        "true_keyboard":"j"
    },
    {
        "stimulus":"stimuli\/match\/match_01b.jpg",
        "true_category":"Julty",
        "true_keyboard":"j"
    },
    {
        "stimulus":"stimuli\/home_plate\/home_plate_09s.jpg",
        "true_category":"Julty",
        "true_keyboard":"j"
    },
    {
        "stimulus":"stimuli\/torch\/torch_02s.jpg",
        "true_category":"Folty",
        "true_keyboard":"f"
    },
    {
        "stimulus":"stimuli\/horse\/horse_07s.jpg",
        "true_category":"Julty",
        "true_keyboard":"j"
    },
    {
        "stimulus":"stimuli\/handbrake\/handbrake_10s.jpg",
        "true_category":"Folty",
        "true_keyboard":"f"
    },
    {
        "stimulus":"stimuli\/gourd\/gourd_14s.jpg",
        "true_category":"Julty",
        "true_keyboard":"j"
    },
    {
        "stimulus":"stimuli\/tripod\/tripod_02s.jpg",
        "true_category":"Folty",
        "true_keyboard":"f"
    },
    {
        "stimulus":"stimuli\/tennis_ball\/tennis_ball_09s.jpg",
        "true_category":"Julty",
        "true_keyboard":"j"
    },
    {
        "stimulus":"stimuli\/pump\/pump_10s.jpg",
        "true_category":"Folty",
        "true_keyboard":"f"
    },
    {
        "stimulus":"stimuli\/straightjacket\/straightjacket_02s.jpg",
        "true_category":"Julty",
        "true_keyboard":"j"
    },
    {
        "stimulus":"stimuli\/gearshift\/gearshift_06s.jpg",
        "true_category":"Folty",
        "true_keyboard":"f"
    },
    {
        "stimulus":"stimuli\/exerciser\/exerciser_01b.jpg",
        "true_category":"Folty",
        "true_keyboard":"f"
    },
    {
        "stimulus":"stimuli\/bell\/bell_07s.jpg",
        "true_category":"Folty",
        "true_keyboard":"f"
    },
    {
        "stimulus":"stimuli\/keyhole\/keyhole_09s.jpg",
        "true_category":"Folty",
        "true_keyboard":"f"
    },
    {
        "stimulus":"stimuli\/bathrobe\/bathrobe_11s.jpg",
        "true_category":"Julty",
        "true_keyboard":"j"
    },
    {
        "stimulus":"stimuli\/ladybug\/ladybug_06s.jpg",
        "true_category":"Julty",
        "true_keyboard":"j"
    },
    {
        "stimulus":"stimuli\/eagle\/eagle_13s.jpg",
        "true_category":"Julty",
        "true_keyboard":"j"
    },
    {
        "stimulus":"stimuli\/shovel\/shovel_04n.jpg",
        "true_category":"Folty",
        "true_keyboard":"f"
    },
    {
        "stimulus":"stimuli\/air_conditioner\/air_conditioner_02s.jpg",
        "true_category":"Julty",
        "true_keyboard":"j"
    },
    {
        "stimulus":"stimuli\/gingerbread_man\/gingerbread_man_11s.jpg",
        "true_category":"Julty",
        "true_keyboard":"j"
    },
    {
        "stimulus":"stimuli\/train_set\/train_set_12s.jpg",
        "true_category":"Folty",
        "true_keyboard":"f"
    },
    {
        "stimulus":"stimuli\/water_filter\/water_filter_11s.jpg",
        "true_category":"Folty",
        "true_keyboard":"f"
    },
    {
        "stimulus":"stimuli\/otter\/otter_05s.jpg",
        "true_category":"Julty",
        "true_keyboard":"j"
    },
    {
        "stimulus":"stimuli\/pinball\/pinball_12s.jpg",
        "true_category":"Julty",
        "true_keyboard":"j"
    },
    {
        "stimulus":"stimuli\/backdrop\/backdrop_02s.jpg",
        "true_category":"Julty",
        "true_keyboard":"j"
    },
    {
        "stimulus":"stimuli\/stopwatch\/stopwatch_02s.jpg",
        "true_category":"Julty",
        "true_keyboard":"j"
    },
    {
        "stimulus":"stimuli\/bib\/bib_05s.jpg",
        "true_category":"Julty",
        "true_keyboard":"j"
    },
    {
        "stimulus":"stimuli\/inkwell\/inkwell_08s.jpg",
        "true_category":"Folty",
        "true_keyboard":"f"
    },
    {
        "stimulus":"stimuli\/stapler\/stapler_06s.jpg",
        "true_category":"Folty",
        "true_keyboard":"f"
    },
    {
        "stimulus":"stimuli\/bandanna\/bandanna_10s.jpg",
        "true_category":"Julty",
        "true_keyboard":"j"
    },
    {
        "stimulus":"stimuli\/nutcracker\/nutcracker_03s.jpg",
        "true_category":"Folty",
        "true_keyboard":"f"
    },
    {
        "stimulus":"stimuli\/train_car\/train_car_13s.jpg",
        "true_category":"Julty",
        "true_keyboard":"j"
    },
    {
        "stimulus":"stimuli\/baseball_bat\/baseball_bat_08s.jpg",
        "true_category":"Julty",
        "true_keyboard":"j"
    },
    {
        "stimulus":"stimuli\/tool\/tool_04s.jpg",
        "true_category":"Folty",
        "true_keyboard":"f"
    },
    {
        "stimulus":"stimuli\/pomegranate\/pomegranate_02s.jpg",
        "true_category":"Julty",
        "true_keyboard":"j"
    },
    {
        "stimulus":"stimuli\/top_hat\/top_hat_07s.jpg",
        "true_category":"Julty",
        "true_keyboard":"j"
    },
    {
        "stimulus":"stimuli\/fruitcake\/fruitcake_01b.jpg",
        "true_category":"Julty",
        "true_keyboard":"j"
    },
    {
        "stimulus":"stimuli\/wedge\/wedge_12s.jpg",
        "true_category":"Julty",
        "true_keyboard":"j"
    },
    {
        "stimulus":"stimuli\/cash_machine\/cash_machine_10s.jpg",
        "true_category":"Folty",
        "true_keyboard":"f"
    },
    {
        "stimulus":"stimuli\/bomb\/bomb_12s.jpg",
        "true_category":"Folty",
        "true_keyboard":"f"
    },
    {
        "stimulus":"stimuli\/smoothie\/smoothie_05s.jpg",
        "true_category":"Julty",
        "true_keyboard":"j"
    },
    {
        "stimulus":"stimuli\/football_helmet\/football_helmet_07s.jpg",
        "true_category":"Julty",
        "true_keyboard":"j"
    },
    {
        "stimulus":"stimuli\/crumb\/crumb_06s.jpg",
        "true_category":"Julty",
        "true_keyboard":"j"
    },
    {
        "stimulus":"stimuli\/cheetah\/cheetah_01b.jpg",
        "true_category":"Julty",
        "true_keyboard":"j"
    },
    {
        "stimulus":"stimuli\/clay\/clay_12s.jpg",
        "true_category":"Julty",
        "true_keyboard":"j"
    },
    {
        "stimulus":"stimuli\/latch\/latch_13s.jpg",
        "true_category":"Folty",
        "true_keyboard":"f"
    },
    {
        "stimulus":"stimuli\/clipper2\/clipper2_04s.jpg",
        "true_category":"Folty",
        "true_keyboard":"f"
    },
    {
        "stimulus":"stimuli\/harp\/harp_06s.jpg",
        "true_category":"Folty",
        "true_keyboard":"f"
    },
    {
        "stimulus":"stimuli\/eggnog\/eggnog_08s.jpg",
        "true_category":"Julty",
        "true_keyboard":"j"
    },
    {
        "stimulus":"stimuli\/tack\/tack_07s.jpg",
        "true_category":"Folty",
        "true_keyboard":"f"
    },
    {
        "stimulus":"stimuli\/flute\/flute_01b.jpg",
        "true_category":"Folty",
        "true_keyboard":"f"
    },
    {
        "stimulus":"stimuli\/rubber_band\/rubber_band_06s.jpg",
        "true_category":"Julty",
        "true_keyboard":"j"
    },
    {
        "stimulus":"stimuli\/eggbeater\/eggbeater_01b.jpg",
        "true_category":"Folty",
        "true_keyboard":"f"
    },
    {
        "stimulus":"stimuli\/telegraph\/telegraph_09s.jpg",
        "true_category":"Folty",
        "true_keyboard":"f"
    },
    {
        "stimulus":"stimuli\/punch2\/punch2_06s.jpg",
        "true_category":"Folty",
        "true_keyboard":"f"
    },
    {
        "stimulus":"stimuli\/anchor\/anchor_10s.jpg",
        "true_category":"Folty",
        "true_keyboard":"f"
    },
    {
        "stimulus":"stimuli\/golf_club\/golf_club_07s.jpg",
        "true_category":"Folty",
        "true_keyboard":"f"
    },
    {
        "stimulus":"stimuli\/dollhouse\/dollhouse_14s.jpg",
        "true_category":"Julty",
        "true_keyboard":"j"
    },
    {
        "stimulus":"stimuli\/fire_pit\/fire_pit_02s.jpg",
        "true_category":"Folty",
        "true_keyboard":"f"
    },
    {
        "stimulus":"stimuli\/barbed_wire\/barbed_wire_15s.jpg",
        "true_category":"Folty",
        "true_keyboard":"f"
    },
    {
        "stimulus":"stimuli\/thorn\/thorn_10s.jpg",
        "true_category":"Julty",
        "true_keyboard":"j"
    },
    {
        "stimulus":"stimuli\/ship\/ship_02s.jpg",
        "true_category":"Julty",
        "true_keyboard":"j"
    },
    {
        "stimulus":"stimuli\/jug\/jug_04s.jpg",
        "true_category":"Folty",
        "true_keyboard":"f"
    },
    {
        "stimulus":"stimuli\/cage\/cage_02s.jpg",
        "true_category":"Folty",
        "true_keyboard":"f"
    },
    {
        "stimulus":"stimuli\/kettle\/kettle_04n.jpg",
        "true_category":"Folty",
        "true_keyboard":"f"
    },
    {
        "stimulus":"stimuli\/fuse\/fuse_04s.jpg",
        "true_category":"Folty",
        "true_keyboard":"f"
    },
    {
        "stimulus":"stimuli\/makeup\/makeup_16s.jpg",
        "true_category":"Julty",
        "true_keyboard":"j"
    },
    {
        "stimulus":"stimuli\/tree_trunk\/tree_trunk_10s.jpg",
        "true_category":"Julty",
        "true_keyboard":"j"
    },
    {
        "stimulus":"stimuli\/oven\/oven_04s.jpg",
        "true_category":"Folty",
        "true_keyboard":"f"
    },
    {
        "stimulus":"stimuli\/crystal_ball\/crystal_ball_05s.jpg",
        "true_category":"Folty",
        "true_keyboard":"f"
    },
    {
        "stimulus":"stimuli\/crank\/crank_09s.jpg",
        "true_category":"Folty",
        "true_keyboard":"f"
    },
    {
        "stimulus":"stimuli\/piano\/piano_13n.jpg",
        "true_category":"Julty",
        "true_keyboard":"j"
    },
    {
        "stimulus":"stimuli\/centrifuge\/centrifuge_01b.jpg",
        "true_category":"Folty",
        "true_keyboard":"f"
    },
    {
        "stimulus":"stimuli\/grille\/grille_07s.jpg",
        "true_category":"Folty",
        "true_keyboard":"f"
    },
    {
        "stimulus":"stimuli\/sidecar\/sidecar_08s.jpg",
        "true_category":"Julty",
        "true_keyboard":"j"
    },
    {
        "stimulus":"stimuli\/scaffold\/scaffold_12s.jpg",
        "true_category":"Folty",
        "true_keyboard":"f"
    },
    {
        "stimulus":"stimuli\/wineglass\/wineglass_10s.jpg",
        "true_category":"Julty",
        "true_keyboard":"j"
    },
    {
        "stimulus":"stimuli\/bone\/bone_02s.jpg",
        "true_category":"Julty",
        "true_keyboard":"j"
    },
    {
        "stimulus":"stimuli\/tie\/tie_06s.jpg",
        "true_category":"Julty",
        "true_keyboard":"j"
    },
    {
        "stimulus":"stimuli\/duct_tape\/duct_tape_02s.jpg",
        "true_category":"Julty",
        "true_keyboard":"j"
    },
    {
        "stimulus":"stimuli\/porthole\/porthole_04s.jpg",
        "true_category":"Folty",
        "true_keyboard":"f"
    },
    {
        "stimulus":"stimuli\/stamp2\/stamp2_08s.jpg",
        "true_category":"Julty",
        "true_keyboard":"j"
    },
    {
        "stimulus":"stimuli\/stair\/stair_03s.jpg",
        "true_category":"Julty",
        "true_keyboard":"j"
    },
    {
        "stimulus":"stimuli\/cooler\/cooler_08s.jpg",
        "true_category":"Julty",
        "true_keyboard":"j"
    },
    {
        "stimulus":"stimuli\/pickax\/pickax_08s.jpg",
        "true_category":"Folty",
        "true_keyboard":"f"
    },
    {
        "stimulus":"stimuli\/marker\/marker_05s.jpg",
        "true_category":"Julty",
        "true_keyboard":"j"
    },
    {
        "stimulus":"stimuli\/slot_machine\/slot_machine_12s.jpg",
        "true_category":"Julty",
        "true_keyboard":"j"
    },
    {
        "stimulus":"stimuli\/staple\/staple_09s.jpg",
        "true_category":"Folty",
        "true_keyboard":"f"
    },
    {
        "stimulus":"stimuli\/airbag\/airbag_01b.jpg",
        "true_category":"Julty",
        "true_keyboard":"j"
    },
    {
        "stimulus":"stimuli\/origami\/origami_08s.jpg",
        "true_category":"Julty",
        "true_keyboard":"j"
    },
    {
        "stimulus":"stimuli\/leash\/leash_03s.jpg",
        "true_category":"Folty",
        "true_keyboard":"f"
    },
    {
        "stimulus":"stimuli\/pencil\/pencil_09s.jpg",
        "true_category":"Julty",
        "true_keyboard":"j"
    },
    {
        "stimulus":"stimuli\/jacket\/jacket_01b.jpg",
        "true_category":"Julty",
        "true_keyboard":"j"
    },
    {
        "stimulus":"stimuli\/coleslaw\/coleslaw_09s.jpg",
        "true_category":"Julty",
        "true_keyboard":"j"
    },
    {
        "stimulus":"stimuli\/paintbrush\/paintbrush_01b.jpg",
        "true_category":"Julty",
        "true_keyboard":"j"
    },
    {
        "stimulus":"stimuli\/flashlight\/flashlight_10s.jpg",
        "true_category":"Folty",
        "true_keyboard":"f"
    },
    {
        "stimulus":"stimuli\/hedgehog\/hedgehog_11n.jpg",
        "true_category":"Julty",
        "true_keyboard":"j"
    },
    {
        "stimulus":"stimuli\/memory_stick\/memory_stick_16s.jpg",
        "true_category":"Folty",
        "true_keyboard":"f"
    },
    {
        "stimulus":"stimuli\/tube_top\/tube_top_05s.jpg",
        "true_category":"Julty",
        "true_keyboard":"j"
    },
    {
        "stimulus":"stimuli\/touchpad\/touchpad_02s.jpg",
        "true_category":"Folty",
        "true_keyboard":"f"
    },
    {
        "stimulus":"stimuli\/briefcase\/briefcase_10s.jpg",
        "true_category":"Folty",
        "true_keyboard":"f"
    },
    {
        "stimulus":"stimuli\/wallet\/wallet_13s.jpg",
        "true_category":"Julty",
        "true_keyboard":"j"
    },
    {
        "stimulus":"stimuli\/crowbar\/crowbar_07n.jpg",
        "true_category":"Folty",
        "true_keyboard":"f"
    },
    {
        "stimulus":"stimuli\/binder\/binder_06s.jpg",
        "true_category":"Julty",
        "true_keyboard":"j"
    },
    {
        "stimulus":"stimuli\/railing\/railing_05s.jpg",
        "true_category":"Folty",
        "true_keyboard":"f"
    },
    {
        "stimulus":"stimuli\/scaffolding\/scaffolding_12n.jpg",
        "true_category":"Folty",
        "true_keyboard":"f"
    },
    {
        "stimulus":"stimuli\/handle\/handle_02s.jpg",
        "true_category":"Folty",
        "true_keyboard":"f"
    },
    {
        "stimulus":"stimuli\/whisk\/whisk_01b.jpg",
        "true_category":"Folty",
        "true_keyboard":"f"
    },
    {
        "stimulus":"stimuli\/ladder\/ladder_01b.jpg",
        "true_category":"Folty",
        "true_keyboard":"f"
    },
    {
        "stimulus":"stimuli\/pocketknife\/pocketknife_08s.jpg",
        "true_category":"Folty",
        "true_keyboard":"f"
    },
    {
        "stimulus":"stimuli\/seatbelt\/seatbelt_09s.jpg",
        "true_category":"Folty",
        "true_keyboard":"f"
    },
    {
        "stimulus":"stimuli\/compass\/compass_03s.jpg",
        "true_category":"Folty",
        "true_keyboard":"f"
    },
    {
        "stimulus":"stimuli\/clover\/clover_14s.jpg",
        "true_category":"Julty",
        "true_keyboard":"j"
    },
    {
        "stimulus":"stimuli\/fingerprint\/fingerprint_01b.jpg",
        "true_category":"Julty",
        "true_keyboard":"j"
    },
    {
        "stimulus":"stimuli\/coffeemaker\/coffeemaker_06s.jpg",
        "true_category":"Folty",
        "true_keyboard":"f"
    },
    {
        "stimulus":"stimuli\/bottle\/bottle_08s.jpg",
        "true_category":"Julty",
        "true_keyboard":"j"
    }
]